__init__.py
main.py
FakeNewsClassifier/__init__.py
FakeNewsClassifier/dt.py
FakeNewsClassifier/models.py
FakeNewsClassifier/nb.py
FakeNewsClassifier/process_text.py
FakeNewsClassifier/saved_model.py
FakeNewsClassifier/scraper.py
FakeNewsClassifier/snn.py
FakeNewsClassifier/svm.py
FakeNewsClassifier/datasets/dezinfo_sk.csv
FakeNewsClassifier/datasets/stopwords.txt
FakeNewsClassifier/saved_models/model_dt.pk
FakeNewsClassifier/saved_models/model_nb.pk
FakeNewsClassifier/saved_models/model_snn.hdf5
FakeNewsClassifier/saved_models/model_snn.pk
FakeNewsClassifier/saved_models/model_svm.pk
FakeNewsClassifier-0.0.22.dist-info/LICENSE
FakeNewsClassifier-0.0.22.dist-info/METADATA
FakeNewsClassifier-0.0.22.dist-info/WHEEL
FakeNewsClassifier-0.0.22.dist-info/top_level.txt
FakeNewsClassifier-0.0.22.dist-info/RECORD
