Metadata-Version: 2.1
Name: FakeNewsClassifier
Version: 0.0.22
Summary: Simple fake news classifier package created for bachelor's thesis 'Detection of Fake News Using Machine Learning'.
Author-email: Matej Koreň <xkoren10@stud.fit.vutbr.cz>
Project-URL: Homepage, https://github.com/xkoren10/BP-2022-23
Classifier: Programming Language :: Python :: 3
Classifier: License :: OSI Approved :: MIT License
Classifier: Operating System :: OS Independent
Requires-Python: >=3.7
License-File: LICENSE
Requires-Dist: pandas
Requires-Dist: scikit-learn
Requires-Dist: matplotlib
Requires-Dist: seaborn
Requires-Dist: nltk
Requires-Dist: tensorflow
Requires-Dist: keras
Requires-Dist: scikeras
Requires-Dist: dill
Requires-Dist: newspaper3k
Requires-Dist: lime
